nonebot_plugin_fuckyou-0.3.0.dist-info/METADATA
nonebot_plugin_fuckyou-0.3.0.dist-info/WHEEL
nonebot_plugin_fuckyou-0.3.0.dist-info/licenses/LICENSE
nonebot_plugin_fuckyou/__init__.py
nonebot_plugin_fuckyou/__main__.py
nonebot_plugin_fuckyou/config.py
nonebot_plugin_fuckyou/const.py
nonebot_plugin_fuckyou/resource/builtin_gentle.json
nonebot_plugin_fuckyou/resource/builtin_violent.json
nonebot_plugin_fuckyou-0.3.0.dist-info/RECORD
