Metadata-Version: 2.1
Name: nonebot-plugin-fuckyou
Version: 0.3.0
Summary: A NoneBot2 plugin designed for curse users
Home-page: https://github.com/lgc2333/nonebot-plugin-fuckyou
Author-Email: student_2333 <lgc2333@126.com>
License: MIT
Project-URL: Homepage, https://github.com/lgc2333/nonebot-plugin-fuckyou
Requires-Python: <4.0,>=3.9
Requires-Dist: nonebot2>=2.2.0
Requires-Dist: nonebot-plugin-alconna>=0.41.1
Requires-Dist: nonebot-plugin-session>=0.3.1
